mrks/__init__.py
mrks/cli.py
mrks/scraper.py
mrks/wsgi.py
mrks/templates/entry.html
mrkoll_scraper-0.3.4.dist-info/LICENSE
mrkoll_scraper-0.3.4.dist-info/METADATA
mrkoll_scraper-0.3.4.dist-info/WHEEL
mrkoll_scraper-0.3.4.dist-info/entry_points.txt
mrkoll_scraper-0.3.4.dist-info/top_level.txt
mrkoll_scraper-0.3.4.dist-info/RECORD
