Metadata-Version: 2.1
Name: mrkoll-scraper
Version: 0.3.4
Summary: mrkoll.se scraper & RSS generator
Home-page: https://github.com/Eboreg/mrkoll-scraper
Author: Robert Huselius
Author-email: robert@huseli.us
License: UNKNOWN
Platform: UNKNOWN
Classifier: Programming Language :: Python :: 3
Classifier: License :: OSI Approved :: GNU General Public License v3 (GPLv3)
Classifier: Operating System :: OS Independent
Classifier: Development Status :: 3 - Alpha
Classifier: Environment :: Console
Classifier: Intended Audience :: Developers
Classifier: Topic :: Internet :: WWW/HTTP :: Dynamic Content
Classifier: Topic :: Internet :: WWW/HTTP :: Indexing/Search
Classifier: Topic :: Software Development :: Libraries :: Python Modules
Requires-Python: >=3.5
Requires-Dist: Jinja2
Requires-Dist: beautifulsoup4
Requires-Dist: feedgen
Requires-Dist: python-dateutil
Requires-Dist: requests
